dftly/__init__.py
dftly/grammar.lark
dftly/nodes.py
dftly/parser.py
dftly/polars.py
dftly/expressions/__init__.py
dftly/expressions/arithmetic.py
dftly/expressions/base.py
dftly/expressions/comparison.py
dftly/expressions/general.py
dftly/expressions/logical.py
dftly-0.0.2.dist-info/licenses/LICENSE
dftly-0.0.2.dist-info/METADATA
dftly-0.0.2.dist-info/WHEEL
dftly-0.0.2.dist-info/top_level.txt
dftly-0.0.2.dist-info/RECORD
