Metadata-Version: 2.4
Name: dftly
Version: 0.0.2
Summary: dftly (pronounced deftly) is a simple library for a safe, expressive, config-file friendly, and readable DSL for encoding simple dataframe operations.
Author-email: Matthew McDermott <mattmcdermott8@gmail.com>
Project-URL: Homepage, https://github.com/mmcdermott/dftly
Project-URL: Issues, https://github.com/mmcdermott/dftly/issues
Classifier: Programming Language :: Python :: 3
Classifier: License :: OSI Approved :: MIT License
Classifier: Operating System :: OS Independent
Requires-Python: >=3.12
License-File: LICENSE
Requires-Dist: PyYAML
Requires-Dist: lark
Requires-Dist: python-dateutil
Provides-Extra: polars
Requires-Dist: polars~=1.33.0; extra == "polars"
Dynamic: license-file
